android_debian_builder/__init__.py
android_debian_builder/__main__.py
android_debian_builder/build.py
android_debian_builder/config.py
android_debian_builder/run_tests.py
android_debian_builder/script.py
android_debian_builder/util.py
android_debian_builder/data/deb.sh
android_debian_builder/data/default-config
android_debian_builder/data/first-time-setup.sh
android_debian_builder/data/init.sh
android_debian_builder/examples/jessie-armhf.cfg
android_debian_builder-1.1.0.data/scripts/android-debian-builder
android_debian_builder-1.1.0.dist-info/DESCRIPTION.rst
android_debian_builder-1.1.0.dist-info/METADATA
android_debian_builder-1.1.0.dist-info/RECORD
android_debian_builder-1.1.0.dist-info/WHEEL
android_debian_builder-1.1.0.dist-info/entry_points.txt
android_debian_builder-1.1.0.dist-info/metadata.json
android_debian_builder-1.1.0.dist-info/top_level.txt
