Metadata-Version: 2.0
Name: android-debian-builder
Version: 1.1.0
Summary: Bootstrap a Debian system in a file, mostly for deploying to Android.
Home-page: https://bitbucket.org/fk/android-debian-builder
Author: Felix Krull
Author-email: f_krull@gmx.de
License: MIT
Platform: Debian
Classifier: Environment :: Console
Classifier: License :: OSI Approved :: MIT License
Classifier: Operating System :: Android
Classifier: Operating System :: POSIX :: Linux
Classifier: Programming Language :: Python :: 3
Classifier: Topic :: System :: Installation/Setup
Requires-Dist: Jinja2 (>=2.7)
